async_vk_api/__init__.py
async_vk_api/api.py
async_vk_api/errors.py
async_vk_api/factories.py
async_vk_api/namespace.py
async_vk_api/retry.py
async_vk_api/throttler.py
async_vk_api-0.6.1.dist-info/METADATA
async_vk_api-0.6.1.dist-info/WHEEL
async_vk_api-0.6.1.dist-info/top_level.txt
async_vk_api-0.6.1.dist-info/RECORD
