Metadata-Version: 2.1
Name: async-vk-api
Version: 0.6.1
Summary: Async VK API built with asks and trio
Home-page: https://github.com/Suenweek/async-vk-api
Author: Roman Novatorov
Author-email: roman.novatorov@gmail.com
License: UNKNOWN
Platform: UNKNOWN
Requires-Dist: asks (==2.2.1)
Requires-Dist: trio
